roboflo/__init__.py
roboflo/helpers.py
roboflo/scheduler.py
roboflo/system.py
roboflo/tasks.py
tests/__init__.py
tests/conftest.py
tests/test_helpers.py
tests/test_scheduler.py
tests/test_system.py
tests/test_tasks.py
tests/test_workers.py
tests/fixtures/__init__.py
tests/fixtures/example_system.py
roboflo-0.2.1.dist-info/LICENSE
roboflo-0.2.1.dist-info/METADATA
roboflo-0.2.1.dist-info/WHEEL
roboflo-0.2.1.dist-info/top_level.txt
roboflo-0.2.1.dist-info/RECORD
