Metadata-Version: 2.1
Name: roboflo
Version: 0.2.1
Summary: Scheduler for automation tasks that involve multiple stations/workers.
Home-page: UNKNOWN
Author: Rishi Kumar
Author-email: rek010@eng.ucsd.edu
License: MIT
Download-URL: https://github.com/rekumar/roboflo
Keywords: research,science,machine,automation
Platform: UNKNOWN
Classifier: Programming Language :: Python :: 3.8
Classifier: Development Status :: 4 - Beta
Classifier: Topic :: Office/Business :: Scheduling
Classifier: Intended Audience :: Manufacturing
Classifier: Intended Audience :: Science/Research
Classifier: Operating System :: OS Independent
Classifier: Topic :: Scientific/Engineering :: Information Analysis
Classifier: Topic :: Scientific/Engineering :: Physics
Classifier: Topic :: Scientific/Engineering :: Chemistry
Classifier: Topic :: Software Development :: Libraries :: Python Modules
Requires-Dist: numpy (~=1.24.0)
Requires-Dist: ortools (~=9.5.2237)
Requires-Dist: matplotlib (~=3.6.2)
Provides-Extra: dev
Requires-Dist: pytest (>=6.2.5) ; extra == 'dev'
